LICENSE
MANIFEST.in
README.rst
setup.cfg
setup.py
versioneer.py
tpDcc/__init__.py
tpDcc/tools/__init__.py
tpDcc/tools/renamer/__init__.py
tpDcc/tools/renamer/__logging__.ini
tpDcc/tools/renamer/__version__.py
tpDcc/tools/renamer/_version.py
tpDcc/tools/renamer/core/__init__.py
tpDcc/tools/renamer/core/client.py
tpDcc/tools/renamer/core/consts.py
tpDcc/tools/renamer/core/controller.py
tpDcc/tools/renamer/core/exceptions.py
tpDcc/tools/renamer/core/model.py
tpDcc/tools/renamer/core/tool.py
tpDcc/tools/renamer/core/toolset.py
tpDcc/tools/renamer/core/utils.py
tpDcc/tools/renamer/core/view.py
tpDcc/tools/renamer/dccs/__init__.py
tpDcc/tools/renamer/dccs/max/__init__.py
tpDcc/tools/renamer/dccs/max/server.py
tpDcc/tools/renamer/dccs/maya/__init__.py
tpDcc/tools/renamer/dccs/maya/server.py
tpDcc/tools/renamer/dccs/unreal/__init__.py
tpDcc/tools/renamer/dccs/unreal/server.py
tpDcc/tools/renamer/resources/icons/color/camera.png
tpDcc/tools/renamer/resources/icons/color/edit.png
tpDcc/tools/renamer/resources/icons/color/file.png
tpDcc/tools/renamer/resources/icons/color/layer.png
tpDcc/tools/renamer/resources/icons/color/light.png
tpDcc/tools/renamer/resources/icons/color/material.png
tpDcc/tools/renamer/resources/icons/color/object.png
tpDcc/tools/renamer/resources/icons/color/rename.png
tpDcc/tools/renamer/resources/icons/default/renamer.png
tpDcc/tools/renamer/resources/images/no_items.png
tpDcc/tools/renamer/widgets/__init__.py
tpDcc/tools/renamer/widgets/autorenamewidget.py
tpDcc/tools/renamer/widgets/categorywidget.py
tpDcc/tools/renamer/widgets/manualrenamewidget.py
tpDcc/tools/renamer/widgets/namespacewidget.py
tpDcc/tools/renamer/widgets/numbersidewidget.py
tpDcc/tools/renamer/widgets/prefixsuffixwidget.py
tpDcc/tools/renamer/widgets/renamerwidget.py
tpDcc/tools/renamer/widgets/replacerwidget.py
tpDcc/tools/renamer/widgets/utilswidget.py
tpDcc_tools_renamer.egg-info/PKG-INFO
tpDcc_tools_renamer.egg-info/SOURCES.txt
tpDcc_tools_renamer.egg-info/dependency_links.txt
tpDcc_tools_renamer.egg-info/not-zip-safe
tpDcc_tools_renamer.egg-info/requires.txt
tpDcc_tools_renamer.egg-info/top_level.txt