Metadata-Version: 2.1
Name: tpDcc-tools-renamer
Version: 0.0.7
Summary: Renamer Tool to easily rename DCC objects in a visual way
Home-page: https://github.com/tpDcc/tpDcc-tools-renamer
Author: Tomas Poveda
Author-email: tpovedatd@gmail.com
License: MIT
Platform: UNKNOWN
Provides-Extra: dev
Provides-Extra: test
